pyqrbtf/__init__.py
pyqrbtf/circles.py
pyqrbtf/dots.py
pyqrbtf/lines.py
pyqrbtf/sp1.py
pyqrbtf/utils/__init__.py
pyqrbtf/utils/base_drawer.py
pyqrbtf/utils/center_module.py
pyqrbtf/utils/const.py
pyqrbtf/utils/figure.py
pyqrbtf/utils/type_table.py
pyqrbtf-0.0.3.dist-info/LICENSE
pyqrbtf-0.0.3.dist-info/METADATA
pyqrbtf-0.0.3.dist-info/WHEEL
pyqrbtf-0.0.3.dist-info/top_level.txt
pyqrbtf-0.0.3.dist-info/RECORD
