Metadata-Version: 2.1
Name: pyqrbtf
Version: 0.0.3
Summary: A project for generating a QR codes in SVG format
Home-page: https://gitlab.com/Myrik/pyqrbtf
Author: Yorsh Siarhei
Author-email: myrik260138@gmail.com
Classifier: Development Status :: 3 - Alpha
Classifier: Intended Audience :: Developers
Classifier: License :: OSI Approved :: MIT License
Classifier: Operating System :: OS Independent
Classifier: Programming Language :: Python :: 3
Classifier: Programming Language :: Python :: 3.8
Classifier: Programming Language :: Python :: 3.9
Requires-Python: >=3.8
License-File: LICENSE
Requires-Dist: qrcode
